array_api_typing.py
array_api_typing-0.0.0.dev0.dist-info/METADATA
array_api_typing-0.0.0.dev0.dist-info/WHEEL
array_api_typing-0.0.0.dev0.dist-info/licenses/LICENSE
array_api_typing-0.0.0.dev0.dist-info/RECORD
